LICENSE
askitsu/__init__.py
askitsu/cache.py
askitsu/client.py
askitsu/error.py
askitsu/http.py
askitsu/models/__init__.py
askitsu/models/anime.py
askitsu/models/character.py
askitsu/models/core.py
askitsu/models/enums.py
askitsu/models/images.py
askitsu/models/manga.py
askitsu/models/users.py
askitsu/queries.py
askitsu-1.0.0.dist-info/LICENSE
askitsu-1.0.0.dist-info/WHEEL
askitsu-1.0.0.dist-info/METADATA
askitsu-1.0.0.dist-info/RECORD
