Metadata-Version: 2.1
Name: askitsu
Version: 1.0.0
Summary: An async API wrapper for Kitsu.io
Home-page: https://github.com/ShomyKohai/askitsu
License: MIT
Keywords: kitsu,kitsu api,kitsu.io,async
Author: ShomyKohai
Requires-Python: >=3.8,<4.0
Classifier: Development Status :: 3 - Alpha
Classifier: Intended Audience :: Developers
Classifier: License :: OSI Approved :: MIT License
Classifier: Natural Language :: English
Classifier: Operating System :: OS Independent
Classifier: Programming Language :: Python :: 3
Classifier: Programming Language :: Python :: 3.10
Classifier: Programming Language :: Python :: 3.8
Classifier: Programming Language :: Python :: 3.9
Classifier: Topic :: Internet
Classifier: Topic :: Software Development :: Libraries
Classifier: Topic :: Software Development :: Libraries :: Python Modules
Classifier: Topic :: Utilities
Classifier: Typing :: Typed
Requires-Dist: aiohttp (>=3.6.0,<4.0.0)
Requires-Dist: colorama (>=0.4.6,<0.5.0)
Project-URL: Bug Tracker, https://github.com/ShomyKohai/askitsu/issues
Project-URL: Documentation, https://askitsu.rtfd.org/
Project-URL: Repository, https://github.com/ShomyKohai/askitsu
